[
  {
    "voters_id": "2000470350",
    "Firstname": "JOAN",
    "Lastname": "ABRITO",
    "Password": "STI_ABRITO",
    "Photo": "../images/male.png"
  },
  {
    "voters_id": "2000463599",
    "Firstname": "WILSON",
    "Lastname": "ABUKE",
    "Password": "STI_ABUKE",
    "Photo": "../images/male.png"
  },
  {
    "voters_id": "2000431843",
    "Firstname": "JAMES IVHO",
    "Lastname": "ADIZAS",
    "Password": "STI_ADIZAS",
    "Photo": "../images/male.png"
  },
  {
    "voters_id": "2000469548",
    "Firstname": "EPRILYN",
    "Lastname": "ALBAO",
    "Password": "STI_ALBAO",
    "Photo": "../images/male.png"
  },
  {
    "voters_id": "2000423533",
    "Firstname": "CRISTHIAN",
    "Lastname": "ALBERO",
    "Password": "STI_ALBERO",
    "Photo": "../images/male.png"
  },
  {
    "voters_id": "2000453246",
    "Firstname": "EDUARDO",
    "Lastname": "ALCORCON",
    "Password": "STI_ALCORCON",
    "Photo": "../images/male.png"
  },
  {
    "voters_id": "2000474413",
    "Firstname": "JHONMARK",
    "Lastname": "ALFONSO",
    "Password": "STI_ALFONSO",
    "Photo": "../images/male.png"
  },
  {
    "voters_id": "2000416427",
    "Firstname": "CLEOFE",
    "Lastname": "ALICO",
    "Password": "STI_ALICO",
    "Photo": "../images/male.png"
  },
  {
    "voters_id": "2000476058",
    "Firstname": "KRISTINA CASSANDRA",
    "Lastname": "ALLERO",
    "Password": "STI_ALLERO",
    "Photo": "../images/male.png"
  },
  {
    "voters_id": "2000475635",
    "Firstname": "CHRISTIAN VINCENT",
    "Lastname": "ALLERO",
    "Password": "STI_ALLERO",
    "Photo": "../images/male.png"
  },
  {
    "voters_id": "2000416206",
    "Firstname": "DIANA MAE",
    "Lastname": "ALMEREZ",
    "Password": "STI_ALMEREZ",
    "Photo": "../images/male.png"
  },
  {
    "voters_id": "2000475077",
    "Firstname": "LENLEE",
    "Lastname": "ALVEZ",
    "Password": "STI_ALVEZ",
    "Photo": "../images/male.png"
  },
  {
    "voters_id": "2000473294",
    "Firstname": "NERESA",
    "Lastname": "AMANTE",
    "Password": "STI_AMANTE",
    "Photo": "../images/male.png"
  },
  {
    "voters_id": "2000469119",
    "Firstname": "CHARMILOTTE",
    "Lastname": "AMBE",
    "Password": "STI_AMBE",
    "Photo": "../images/male.png"
  },
  {
    "voters_id": "2000420295",
    "Firstname": "SHERILLE",
    "Lastname": "AMPARADO",
    "Password": "STI_AMPARADO",
    "Photo": "../images/male.png"
  },
  {
    "voters_id": "2000472260",
    "Firstname": "RICO",
    "Lastname": "AMPOAN",
    "Password": "STI_AMPOAN",
    "Photo": "../images/male.png"
  },
  {
    "voters_id": "2000474183",
    "Firstname": "JOMAR",
    "Lastname": "AMPONG",
    "Password": "STI_AMPONG",
    "Photo": "../images/male.png"
  },
  {
    "voters_id": "2000476197",
    "Firstname": "LEOMEL",
    "Lastname": "ANDULTE",
    "Password": "STI_ANDULTE",
    "Photo": "../images/male.png"
  },
  {
    "voters_id": "2000400775",
    "Firstname": "ETHEL",
    "Lastname": "ANDULTE",
    "Password": "STI_ANDULTE",
    "Photo": "../images/male.png"
  },
  {
    "voters_id": "2000421481",
    "Firstname": "MARY GABRIELLE",
    "Lastname": "ANGELIO",
    "Password": "STI_ANGELIO",
    "Photo": "../images/male.png"
  },
  {
    "voters_id": "2000475447",
    "Firstname": "KURT",
    "Lastname": "ANIBAN",
    "Password": "STI_ANIBAN",
    "Photo": "../images/male.png"
  },
  {
    "voters_id": "2000472002",
    "Firstname": "KATHLEEN DANICA",
    "Lastname": "ANIBAN",
    "Password": "STI_ANIBAN",
    "Photo": "../images/male.png"
  },
  {
    "voters_id": "2000476021",
    "Firstname": "SYREL MAE",
    "Lastname": "ANQUE",
    "Password": "STI_ANQUE",
    "Photo": "../images/male.png"
  },
  {
    "voters_id": "2000474333",
    "Firstname": "RENZ CYRUS",
    "Lastname": "ANQUE",
    "Password": "STI_ANQUE",
    "Photo": "../images/male.png"
  },
  {
    "voters_id": "2000434808",
    "Firstname": "ROLANDO JR.",
    "Lastname": "ANQUILAN",
    "Password": "STI_ANQUILAN",
    "Photo": "../images/male.png"
  },
  {
    "voters_id": "2000406261",
    "Firstname": "JOLLY ANNE",
    "Lastname": "ARAZA",
    "Password": "STI_ARAZA",
    "Photo": "../images/male.png"
  },
  {
    "voters_id": "2000475405",
    "Firstname": "JOVY ROSE",
    "Lastname": "ARA\u00d1A",
    "Password": "STI_ARA\u00d1A",
    "Photo": "../images/male.png"
  },
  {
    "voters_id": "2000418311",
    "Firstname": "PERICULO III",
    "Lastname": "ARGENIO",
    "Password": "STI_ARGENIO",
    "Photo": "../images/male.png"
  },
  {
    "voters_id": "2000425475",
    "Firstname": "JHONCEL",
    "Lastname": "ARIBAS",
    "Password": "STI_ARIBAS",
    "Photo": "../images/male.png"
  },
  {
    "voters_id": "2000468558",
    "Firstname": "ARNEL",
    "Lastname": "ARISGA",
    "Password": "STI_ARISGA",
    "Photo": "../images/male.png"
  },
  {
    "voters_id": "2000417032",
    "Firstname": "ALFREDO III",
    "Lastname": "ARRIEGA",
    "Password": "STI_ARRIEGA",
    "Photo": "../images/male.png"
  },
  {
    "voters_id": "2000472715",
    "Firstname": "JULIUS",
    "Lastname": "ATCHASO",
    "Password": "STI_ATCHASO",
    "Photo": "../images/male.png"
  },
  {
    "voters_id": "2000473908",
    "Firstname": "JOLAS",
    "Lastname": "ATCHASO",
    "Password": "STI_ATCHASO",
    "Photo": "../images/male.png"
  },
  {
    "voters_id": "2000409223",
    "Firstname": "KRES RAZTEL",
    "Lastname": "ATIS",
    "Password": "STI_ATIS",
    "Photo": "../images/male.png"
  },
  {
    "voters_id": "2000475069",
    "Firstname": "RENZ",
    "Lastname": "BADUA",
    "Password": "STI_BADUA",
    "Photo": "../images/male.png"
  },
  {
    "voters_id": "2000460386",
    "Firstname": "IRISH MITCH",
    "Lastname": "BAGRO",
    "Password": "STI_BAGRO",
    "Photo": "../images/male.png"
  },
  {
    "voters_id": "2000438546",
    "Firstname": "JOHN CARL",
    "Lastname": "BALAWANG",
    "Password": "STI_BALAWANG",
    "Photo": "../images/male.png"
  },
  {
    "voters_id": "2000466509",
    "Firstname": "ROSE ANN",
    "Lastname": "BALIOS",
    "Password": "STI_BALIOS",
    "Photo": "../images/male.png"
  },
  {
    "voters_id": "2000394793",
    "Firstname": "JHONPERSON",
    "Lastname": "BANSAY",
    "Password": "STI_BANSAY",
    "Photo": "../images/male.png"
  },
  {
    "voters_id": "2000394801",
    "Firstname": "CRIS VENMAR",
    "Lastname": "BANSAY",
    "Password": "STI_BANSAY",
    "Photo": "../images/male.png"
  },
  {
    "voters_id": "2000474788",
    "Firstname": "JAZRYL BUDZ",
    "Lastname": "BANTASAN",
    "Password": "STI_BANTASAN",
    "Photo": "../images/male.png"
  },
  {
    "voters_id": "2000402167",
    "Firstname": "JENNIEL",
    "Lastname": "BANTAYAN",
    "Password": "STI_BANTAYAN",
    "Photo": "../images/male.png"
  },
  {
    "voters_id": "2000467615",
    "Firstname": "NOEMI",
    "Lastname": "BARANDINO",
    "Password": "STI_BARANDINO",
    "Photo": "../images/male.png"
  },
  {
    "voters_id": "2000412289",
    "Firstname": "MICHELLE",
    "Lastname": "BAYAGUSA",
    "Password": "STI_BAYAGUSA",
    "Photo": "../images/male.png"
  },
  {
    "voters_id": "2000436935",
    "Firstname": "JOHN PAUL CARL",
    "Lastname": "BAYLON",
    "Password": "STI_BAYLON",
    "Photo": "../images/male.png"
  },
  {
    "voters_id": "2000401412",
    "Firstname": "JESMAR",
    "Lastname": "BAYONACO",
    "Password": "STI_BAYONACO",
    "Photo": "../images/male.png"
  },
  {
    "voters_id": "2000475454",
    "Firstname": "JOHN VINCENT",
    "Lastname": "BAYONON",
    "Password": "STI_BAYONON",
    "Photo": "../images/male.png"
  },
  {
    "voters_id": "2000475162",
    "Firstname": "RALPH ANGELO",
    "Lastname": "BEDIO",
    "Password": "STI_BEDIO",
    "Photo": "../images/male.png"
  },
  {
    "voters_id": "2000468958",
    "Firstname": "RIAN CARLA",
    "Lastname": "BEDIO",
    "Password": "STI_BEDIO",
    "Photo": "../images/male.png"
  },
  {
    "voters_id": "2000408713",
    "Firstname": "MARIANNE",
    "Lastname": "BEDNARCZYK",
    "Password": "STI_BEDNARCZYK",
    "Photo": "../images/male.png"
  },
  {
    "voters_id": "2000417353",
    "Firstname": "MELISSA",
    "Lastname": "BELANGIGUE",
    "Password": "STI_BELANGIGUE",
    "Photo": "../images/male.png"
  },
  {
    "voters_id": "2000429364",
    "Firstname": "JOSHUA",
    "Lastname": "BESCORO",
    "Password": "STI_BESCORO",
    "Photo": "../images/male.png"
  },
  {
    "voters_id": "2000464472",
    "Firstname": "ZIAN",
    "Lastname": "BESO",
    "Password": "STI_BESO",
    "Photo": "../images/male.png"
  },
  {
    "voters_id": "2000463398",
    "Firstname": "KARL PABLO",
    "Lastname": "BIJASA",
    "Password": "STI_BIJASA",
    "Photo": "../images/male.png"
  },
  {
    "voters_id": "2000469912",
    "Firstname": "KRISTOPHER DAVE",
    "Lastname": "BINDOY",
    "Password": "STI_BINDOY",
    "Photo": "../images/male.png"
  },
  {
    "voters_id": "2000435086",
    "Firstname": "SEAN ALMICH",
    "Lastname": "BOGO",
    "Password": "STI_BOGO",
    "Photo": "../images/male.png"
  },
  {
    "voters_id": "2000468016",
    "Firstname": "ALEXA THESS",
    "Lastname": "BOLANTE",
    "Password": "STI_BOLANTE",
    "Photo": "../images/male.png"
  },
  {
    "voters_id": "2000475470",
    "Firstname": "ALBE ANN",
    "Lastname": "BOLLER",
    "Password": "STI_BOLLER",
    "Photo": "../images/male.png"
  },
  {
    "voters_id": "2000472004",
    "Firstname": "PRINCESS  MAUI",
    "Lastname": "BONGCALES",
    "Password": "STI_BONGCALES",
    "Photo": "../images/male.png"
  },
  {
    "voters_id": "2000398575",
    "Firstname": "JAYHAN NOVIE",
    "Lastname": "BONGUIT",
    "Password": "STI_BONGUIT",
    "Photo": "../images/male.png"
  },
  {
    "voters_id": "2000380779",
    "Firstname": "LIZEL",
    "Lastname": "BORDEN",
    "Password": "STI_BORDEN",
    "Photo": "../images/male.png"
  },
  {
    "voters_id": "2000457328",
    "Firstname": "ASHELEY",
    "Lastname": "BOROC",
    "Password": "STI_BOROC",
    "Photo": "../images/male.png"
  },
  {
    "voters_id": "2000459752",
    "Firstname": "JAN CARLO",
    "Lastname": "BORROMEO",
    "Password": "STI_BORROMEO",
    "Photo": "../images/male.png"
  },
  {
    "voters_id": "2000413590",
    "Firstname": "REGINE",
    "Lastname": "BOSQUE",
    "Password": "STI_BOSQUE",
    "Photo": "../images/male.png"
  },
  {
    "voters_id": "2000474066",
    "Firstname": "KATRINA JANE",
    "Lastname": "BRANZUELA",
    "Password": "STI_BRANZUELA",
    "Photo": "../images/male.png"
  },
  {
    "voters_id": "2000414351",
    "Firstname": "LOLITO JR.",
    "Lastname": "CAAMUD",
    "Password": "STI_CAAMUD",
    "Photo": "../images/male.png"
  },
  {
    "voters_id": "2000430068",
    "Firstname": "SHALVIN JOHN",
    "Lastname": "CABARLES",
    "Password": "STI_CABARLES",
    "Photo": "../images/male.png"
  },
  {
    "voters_id": "2000475624",
    "Firstname": "GILBERT JR.",
    "Lastname": "CABELING",
    "Password": "STI_CABELING",
    "Photo": "../images/male.png"
  },
  {
    "voters_id": "2000475407",
    "Firstname": "TANA MARIA",
    "Lastname": "CABER",
    "Password": "STI_CABER",
    "Photo": "../images/male.png"
  },
  {
    "voters_id": "2000386309",
    "Firstname": "RUBELYN",
    "Lastname": "CABRERA",
    "Password": "STI_CABRERA",
    "Photo": "../images/male.png"
  },
  {
    "voters_id": "2000459716",
    "Firstname": "CATHY",
    "Lastname": "CAGOMOC",
    "Password": "STI_CAGOMOC",
    "Photo": "../images/male.png"
  },
  {
    "voters_id": "2000457337",
    "Firstname": "PRINCE NOAH",
    "Lastname": "CAGUIMBAL",
    "Password": "STI_CAGUIMBAL",
    "Photo": "../images/male.png"
  },
  {
    "voters_id": "2000472743",
    "Firstname": "OXYNTHIA YVETTE",
    "Lastname": "CAJEME",
    "Password": "STI_CAJEME",
    "Photo": "../images/male.png"
  },
  {
    "voters_id": "2000470696",
    "Firstname": "RHEHANNA",
    "Lastname": "CAJURAO",
    "Password": "STI_CAJURAO",
    "Photo": "../images/male.png"
  },
  {
    "voters_id": "2000460296",
    "Firstname": "RUBY GRACE",
    "Lastname": "CALAGOS",
    "Password": "STI_CALAGOS",
    "Photo": "../images/male.png"
  },
  {
    "voters_id": "2000467796",
    "Firstname": "DANDWIN ACE",
    "Lastname": "CALAGOS",
    "Password": "STI_CALAGOS",
    "Photo": "../images/male.png"
  },
  {
    "voters_id": "2000475467",
    "Firstname": "LEWIS JOHN",
    "Lastname": "CALDERON",
    "Password": "STI_CALDERON",
    "Photo": "../images/male.png"
  },
  {
    "voters_id": "2000471333",
    "Firstname": "JOVELYN",
    "Lastname": "CALIPAY",
    "Password": "STI_CALIPAY",
    "Photo": "../images/male.png"
  },
  {
    "voters_id": "2000424939",
    "Firstname": "MARK KENNITH",
    "Lastname": "CALIPAY",
    "Password": "STI_CALIPAY",
    "Photo": "../images/male.png"
  },
  {
    "voters_id": "2000468463",
    "Firstname": "JASON",
    "Lastname": "CANO",
    "Password": "STI_CANO",
    "Photo": "../images/male.png"
  },
  {
    "voters_id": "2000473749",
    "Firstname": "DARYL",
    "Lastname": "CAPELLAN",
    "Password": "STI_CAPELLAN",
    "Photo": "../images/male.png"
  },
  {
    "voters_id": "2000427388",
    "Firstname": "RONALYN",
    "Lastname": "CAPONGCOL",
    "Password": "STI_CAPONGCOL",
    "Photo": "../images/male.png"
  },
  {
    "voters_id": "2000429357",
    "Firstname": "CHARINEL",
    "Lastname": "CARBO",
    "Password": "STI_CARBO",
    "Photo": "../images/male.png"
  },
  {
    "voters_id": "2000413096",
    "Firstname": "SHERELLYN",
    "Lastname": "CARIG",
    "Password": "STI_CARIG",
    "Photo": "../images/male.png"
  },
  {
    "voters_id": "2000473317",
    "Firstname": "ALIZA MAE",
    "Lastname": "CASIANO",
    "Password": "STI_CASIANO",
    "Photo": "../images/male.png"
  },
  {
    "voters_id": "2000473131",
    "Firstname": "JANUS",
    "Lastname": "CASPE",
    "Password": "STI_CASPE",
    "Photo": "../images/male.png"
  },
  {
    "voters_id": "2000464469",
    "Firstname": "ANTHONY",
    "Lastname": "CASTILLANO",
    "Password": "STI_CASTILLANO",
    "Photo": "../images/male.png"
  },
  {
    "voters_id": "2000464998",
    "Firstname": "NICOLE",
    "Lastname": "CASTRO",
    "Password": "STI_CASTRO",
    "Photo": "../images/male.png"
  },
  {
    "voters_id": "2000472734",
    "Firstname": "CARL BENEDICT",
    "Lastname": "CATALAN",
    "Password": "STI_CATALAN",
    "Photo": "../images/male.png"
  },
  {
    "voters_id": "2000466053",
    "Firstname": "JEMIMA",
    "Lastname": "CATANGUE",
    "Password": "STI_CATANGUE",
    "Photo": "../images/male.png"
  },
  {
    "voters_id": "2000468514",
    "Firstname": "SHAINA MARIE",
    "Lastname": "CATARUS",
    "Password": "STI_CATARUS",
    "Photo": "../images/male.png"
  },
  {
    "voters_id": "2000475622",
    "Firstname": "DHOLCIE",
    "Lastname": "CESARIO",
    "Password": "STI_CESARIO",
    "Photo": "../images/male.png"
  },
  {
    "voters_id": "2000472298",
    "Firstname": "RENAN",
    "Lastname": "CLAUDIO",
    "Password": "STI_CLAUDIO",
    "Photo": "../images/male.png"
  },
  {
    "voters_id": "2000428338",
    "Firstname": "ERWIN JR.",
    "Lastname": "COMEDIA",
    "Password": "STI_COMEDIA",
    "Photo": "../images/male.png"
  },
  {
    "voters_id": "2000472288",
    "Firstname": "JANRIE",
    "Lastname": "COMPETO",
    "Password": "STI_COMPETO",
    "Photo": "../images/male.png"
  },
  {
    "voters_id": "2000427054",
    "Firstname": "RAINER",
    "Lastname": "CONTRIDAS",
    "Password": "STI_CONTRIDAS",
    "Photo": "../images/male.png"
  },
  {
    "voters_id": "2000472893",
    "Firstname": "MILVEN",
    "Lastname": "COSCULLA",
    "Password": "STI_COSCULLA",
    "Photo": "../images/male.png"
  },
  {
    "voters_id": "2000424360",
    "Firstname": "JOHN MARK",
    "Lastname": "DACARA",
    "Password": "STI_DACARA",
    "Photo": "../images/male.png"
  },
  {
    "voters_id": "2000420605",
    "Firstname": "DEXTER",
    "Lastname": "DACUTANAN",
    "Password": "STI_DACUTANAN",
    "Photo": "../images/male.png"
  },
  {
    "voters_id": "2000468576",
    "Firstname": "NELLA",
    "Lastname": "DACUYAN",
    "Password": "STI_DACUYAN",
    "Photo": "../images/male.png"
  },
  {
    "voters_id": "2000475368",
    "Firstname": "ANGELICA",
    "Lastname": "DAGOHOY",
    "Password": "STI_DAGOHOY",
    "Photo": "../images/male.png"
  },
  {
    "voters_id": "2000475492",
    "Firstname": "DAVE CLARINCE",
    "Lastname": "DAGUMAN",
    "Password": "STI_DAGUMAN",
    "Photo": "../images/male.png"
  },
  {
    "voters_id": "2000418602",
    "Firstname": "ROGELIO",
    "Lastname": "DAGUMAN",
    "Password": "STI_DAGUMAN",
    "Photo": "../images/male.png"
  },
  {
    "voters_id": "2000431925",
    "Firstname": "MARIEL",
    "Lastname": "DAGUMAN",
    "Password": "STI_DAGUMAN",
    "Photo": "../images/male.png"
  },
  {
    "voters_id": "2000459015",
    "Firstname": "SUMMER ANN",
    "Lastname": "DAILEY",
    "Password": "STI_DAILEY",
    "Photo": "../images/male.png"
  },
  {
    "voters_id": "2000423527",
    "Firstname": "ANDREW",
    "Lastname": "DALICANO",
    "Password": "STI_DALICANO",
    "Photo": "../images/male.png"
  },
  {
    "voters_id": "2000418585",
    "Firstname": "SHANN CARLO",
    "Lastname": "DAMALLA",
    "Password": "STI_DAMALLA",
    "Photo": "../images/male.png"
  },
  {
    "voters_id": "2000413850",
    "Firstname": "JOHN LLOYD",
    "Lastname": "DAUBA",
    "Password": "STI_DAUBA",
    "Photo": "../images/male.png"
  },
  {
    "voters_id": "2000470793",
    "Firstname": "JOSH",
    "Lastname": "DE GUZMAN",
    "Password": "STI_DE GUZMAN",
    "Photo": "../images/male.png"
  },
  {
    "voters_id": "2000473238",
    "Firstname": "ROCYDEL",
    "Lastname": "DE JUAN",
    "Password": "STI_DE JUAN",
    "Photo": "../images/male.png"
  },
  {
    "voters_id": "2000420299",
    "Firstname": "QUENNIE",
    "Lastname": "DELA BUENA",
    "Password": "STI_DELA BUENA",
    "Photo": "../images/male.png"
  },
  {
    "voters_id": "2000475634",
    "Firstname": "JUSTIN ANTHONY",
    "Lastname": "DELA TONGA",
    "Password": "STI_DELA TONGA",
    "Photo": "../images/male.png"
  },
  {
    "voters_id": "2000408237",
    "Firstname": "BERNADETTE",
    "Lastname": "DELOS REYES",
    "Password": "STI_DELOS REYES",
    "Photo": "../images/male.png"
  },
  {
    "voters_id": "2000424671",
    "Firstname": "ANNA LORAINE",
    "Lastname": "DELOS SANTOS",
    "Password": "STI_DELOS SANTOS",
    "Photo": "../images/male.png"
  },
  {
    "voters_id": "2000410737",
    "Firstname": "MARK ABENSON",
    "Lastname": "DERAYA",
    "Password": "STI_DERAYA",
    "Photo": "../images/male.png"
  },
  {
    "voters_id": "2000474668",
    "Firstname": "ARRIANE",
    "Lastname": "DIAZ",
    "Password": "STI_DIAZ",
    "Photo": "../images/male.png"
  },
  {
    "voters_id": "2000420328",
    "Firstname": "KERBY",
    "Lastname": "DIMAKILING",
    "Password": "STI_DIMAKILING",
    "Photo": "../images/male.png"
  },
  {
    "voters_id": "2000366585",
    "Firstname": "STEPHANIE JOY",
    "Lastname": "DOCIL",
    "Password": "STI_DOCIL",
    "Photo": "../images/male.png"
  },
  {
    "voters_id": "2000470550",
    "Firstname": "JAN RYSTER",
    "Lastname": "DOMAYAN",
    "Password": "STI_DOMAYAN",
    "Photo": "../images/male.png"
  },
  {
    "voters_id": "2000427068",
    "Firstname": "DONYL",
    "Lastname": "DOMINGO",
    "Password": "STI_DOMINGO",
    "Photo": "../images/male.png"
  },
  {
    "voters_id": "2000473888",
    "Firstname": "JHON RHEMEN",
    "Lastname": "DULLOSO",
    "Password": "STI_DULLOSO",
    "Photo": "../images/male.png"
  },
  {
    "voters_id": "2000473230",
    "Firstname": "GABRIELA",
    "Lastname": "DUMAYAN",
    "Password": "STI_DUMAYAN",
    "Photo": "../images/male.png"
  },
  {
    "voters_id": "2000424283",
    "Firstname": "MARGILENE",
    "Lastname": "DURO",
    "Password": "STI_DURO",
    "Photo": "../images/male.png"
  },
  {
    "voters_id": "2000462691",
    "Firstname": "LOIDA",
    "Lastname": "ENDIZA",
    "Password": "STI_ENDIZA",
    "Photo": "../images/male.png"
  },
  {
    "voters_id": "2000474308",
    "Firstname": "JONA",
    "Lastname": "EPA",
    "Password": "STI_EPA",
    "Photo": "../images/male.png"
  },
  {
    "voters_id": "2000471766",
    "Firstname": "ROQUELLO LANCE",
    "Lastname": "ERO",
    "Password": "STI_ERO",
    "Photo": "../images/male.png"
  },
  {
    "voters_id": "2000475410",
    "Firstname": "JANELLE",
    "Lastname": "ESCOBAR",
    "Password": "STI_ESCOBAR",
    "Photo": "../images/male.png"
  },
  {
    "voters_id": "2000466702",
    "Firstname": "KYLE MARK",
    "Lastname": "ESMUNDO",
    "Password": "STI_ESMUNDO",
    "Photo": "../images/male.png"
  },
  {
    "voters_id": "2000398437",
    "Firstname": "PATRECIA",
    "Lastname": "ESPINA",
    "Password": "STI_ESPINA",
    "Photo": "../images/male.png"
  },
  {
    "voters_id": "2000435140",
    "Firstname": "AIZA",
    "Lastname": "ESTRELLES",
    "Password": "STI_ESTRELLES",
    "Photo": "../images/male.png"
  },
  {
    "voters_id": "2000455610",
    "Firstname": "SAMANTHA NICOLE",
    "Lastname": "ETABLE",
    "Password": "STI_ETABLE",
    "Photo": "../images/male.png"
  },
  {
    "voters_id": "2000430024",
    "Firstname": "ANTONIETTE MARIE",
    "Lastname": "FABRIGARAS",
    "Password": "STI_FABRIGARAS",
    "Photo": "../images/male.png"
  },
  {
    "voters_id": "2000427644",
    "Firstname": "ANGELO",
    "Lastname": "FELIZARIO",
    "Password": "STI_FELIZARIO",
    "Photo": "../images/male.png"
  },
  {
    "voters_id": "2000420127",
    "Firstname": "CHRISTAL MHAE",
    "Lastname": "FERNANDEZ",
    "Password": "STI_FERNANDEZ",
    "Photo": "../images/male.png"
  },
  {
    "voters_id": "2000432512",
    "Firstname": "VINCENT JAY",
    "Lastname": "FLORIDA",
    "Password": "STI_FLORIDA",
    "Photo": "../images/male.png"
  },
  {
    "voters_id": "2000458676",
    "Firstname": "JOSEPH JAY",
    "Lastname": "FLORIDA",
    "Password": "STI_FLORIDA",
    "Photo": "../images/male.png"
  },
  {
    "voters_id": "2000431660",
    "Firstname": "LEA",
    "Lastname": "FRANCISCO",
    "Password": "STI_FRANCISCO",
    "Photo": "../images/male.png"
  },
  {
    "voters_id": "2000424871",
    "Firstname": "CARLOS",
    "Lastname": "FRANCO",
    "Password": "STI_FRANCO",
    "Photo": "../images/male.png"
  },
  {
    "voters_id": "2000472035",
    "Firstname": "AL JAN RYGH",
    "Lastname": "FRANCO",
    "Password": "STI_FRANCO",
    "Photo": "../images/male.png"
  },
  {
    "voters_id": "2000466457",
    "Firstname": "JOHN CARLO",
    "Lastname": "FUENTEBLANCA",
    "Password": "STI_FUENTEBLANCA",
    "Photo": "../images/male.png"
  },
  {
    "voters_id": "2000425348",
    "Firstname": "ALLYSSA",
    "Lastname": "GALIBO",
    "Password": "STI_GALIBO",
    "Photo": "../images/male.png"
  },
  {
    "voters_id": "2000475364",
    "Firstname": "REA MAE",
    "Lastname": "GALLARDO",
    "Password": "STI_GALLARDO",
    "Photo": "../images/male.png"
  },
  {
    "voters_id": "2000420032",
    "Firstname": "AIZA RONA",
    "Lastname": "GARCIA",
    "Password": "STI_GARCIA",
    "Photo": "../images/male.png"
  },
  {
    "voters_id": "2000359996",
    "Firstname": "ALFIER NAN",
    "Lastname": "GASPAN",
    "Password": "STI_GASPAN",
    "Photo": "../images/male.png"
  },
  {
    "voters_id": "2000470977",
    "Firstname": "ALOHA DAWN",
    "Lastname": "GEPAYO",
    "Password": "STI_GEPAYO",
    "Photo": "../images/male.png"
  },
  {
    "voters_id": "2000472248",
    "Firstname": "MILDRED",
    "Lastname": "GOLES",
    "Password": "STI_GOLES",
    "Photo": "../images/male.png"
  },
  {
    "voters_id": "2000465899",
    "Firstname": "MARK JUSTIN",
    "Lastname": "GOLES",
    "Password": "STI_GOLES",
    "Photo": "../images/male.png"
  },
  {
    "voters_id": "2000475191",
    "Firstname": "JOSEPH JERONE",
    "Lastname": "GONZAGA",
    "Password": "STI_GONZAGA",
    "Photo": "../images/male.png"
  },
  {
    "voters_id": "2000428068",
    "Firstname": "JAMEL",
    "Lastname": "GONZALES",
    "Password": "STI_GONZALES",
    "Photo": "../images/male.png"
  },
  {
    "voters_id": "2000472030",
    "Firstname": "JEAN",
    "Lastname": "GOTIDO",
    "Password": "STI_GOTIDO",
    "Photo": "../images/male.png"
  },
  {
    "voters_id": "2000473919",
    "Firstname": "ARLENE",
    "Lastname": "GUEVARRA",
    "Password": "STI_GUEVARRA",
    "Photo": "../images/male.png"
  },
  {
    "voters_id": "2000467783",
    "Firstname": "JHUN LEE",
    "Lastname": "GUIT GUIT",
    "Password": "STI_GUIT GUIT",
    "Photo": "../images/male.png"
  },
  {
    "voters_id": "2000425436",
    "Firstname": "JERICH",
    "Lastname": "HEPAYO",
    "Password": "STI_HEPAYO",
    "Photo": "../images/male.png"
  },
  {
    "voters_id": "2000427464",
    "Firstname": "KEN JAMES",
    "Lastname": "IBAJO",
    "Password": "STI_IBAJO",
    "Photo": "../images/male.png"
  },
  {
    "voters_id": "2000470070",
    "Firstname": "JOHN ARIES",
    "Lastname": "IGNACIO",
    "Password": "STI_IGNACIO",
    "Photo": "../images/male.png"
  },
  {
    "voters_id": "2000471273",
    "Firstname": "CHRISTAL JADE",
    "Lastname": "JALAYAJAY",
    "Password": "STI_JALAYAJAY",
    "Photo": "../images/male.png"
  },
  {
    "voters_id": "2000416076",
    "Firstname": "ERICA",
    "Lastname": "JALAYAJAY",
    "Password": "STI_JALAYAJAY",
    "Photo": "../images/male.png"
  },
  {
    "voters_id": "2000468112",
    "Firstname": "MA. JESSICA",
    "Lastname": "JAQUE",
    "Password": "STI_JAQUE",
    "Photo": "../images/male.png"
  },
  {
    "voters_id": "2000476085",
    "Firstname": "GABRIEL RYNDON",
    "Lastname": "JAVINES",
    "Password": "STI_JAVINES",
    "Photo": "../images/male.png"
  },
  {
    "voters_id": "2000429661",
    "Firstname": "ANDREA JONES",
    "Lastname": "JAYME",
    "Password": "STI_JAYME",
    "Photo": "../images/male.png"
  },
  {
    "voters_id": "2000472222",
    "Firstname": "HARREL",
    "Lastname": "JULATON",
    "Password": "STI_JULATON",
    "Photo": "../images/male.png"
  },
  {
    "voters_id": "2000440841",
    "Firstname": "JOSHUA",
    "Lastname": "JULATON",
    "Password": "STI_JULATON",
    "Photo": "../images/male.png"
  },
  {
    "voters_id": "2000461953",
    "Firstname": "ANGELICA",
    "Lastname": "JUMADAY",
    "Password": "STI_JUMADAY",
    "Photo": "../images/male.png"
  },
  {
    "voters_id": "2000426457",
    "Firstname": "KLEAH",
    "Lastname": "LADRERO",
    "Password": "STI_LADRERO",
    "Photo": "../images/male.png"
  },
  {
    "voters_id": "2000464945",
    "Firstname": "RACHELLE",
    "Lastname": "LAGRIMAS",
    "Password": "STI_LAGRIMAS",
    "Photo": "../images/male.png"
  },
  {
    "voters_id": "2000427204",
    "Firstname": "LOUIERA IGNACIA",
    "Lastname": "LAOYON",
    "Password": "STI_LAOYON",
    "Photo": "../images/male.png"
  },
  {
    "voters_id": "2000463791",
    "Firstname": "JOANIE",
    "Lastname": "LAOYON",
    "Password": "STI_LAOYON",
    "Photo": "../images/male.png"
  },
  {
    "voters_id": "2000414048",
    "Firstname": "MARIA FELIZ",
    "Lastname": "LASACA",
    "Password": "STI_LASACA",
    "Photo": "../images/male.png"
  },
  {
    "voters_id": "2000470628",
    "Firstname": "MA.CHRISTINE",
    "Lastname": "LAYONG",
    "Password": "STI_LAYONG",
    "Photo": "../images/male.png"
  },
  {
    "voters_id": "2000389689",
    "Firstname": "LEEANN",
    "Lastname": "LEA\u00d1O",
    "Password": "STI_LEA\u00d1O",
    "Photo": "../images/male.png"
  },
  {
    "voters_id": "2000473282",
    "Firstname": "ADRIANA CAREL",
    "Lastname": "LEGASPI",
    "Password": "STI_LEGASPI",
    "Photo": "../images/male.png"
  },
  {
    "voters_id": "2000424322",
    "Firstname": "CHERLYN",
    "Lastname": "LEGATONA",
    "Password": "STI_LEGATONA",
    "Photo": "../images/male.png"
  },
  {
    "voters_id": "2000463802",
    "Firstname": "MONYTHE ELIZABETH",
    "Lastname": "LEGUIDLEGUID",
    "Password": "STI_LEGUIDLEGUID",
    "Photo": "../images/male.png"
  },
  {
    "voters_id": "2000426022",
    "Firstname": "REYMARK",
    "Lastname": "LENTEJAS",
    "Password": "STI_LENTEJAS",
    "Photo": "../images/male.png"
  },
  {
    "voters_id": "2000473553",
    "Firstname": "JOCELYN",
    "Lastname": "LOBERIANO",
    "Password": "STI_LOBERIANO",
    "Photo": "../images/male.png"
  },
  {
    "voters_id": "2000470878",
    "Firstname": "MAXINE",
    "Lastname": "LOBO",
    "Password": "STI_LOBO",
    "Photo": "../images/male.png"
  },
  {
    "voters_id": "2000292206",
    "Firstname": "ANALYN",
    "Lastname": "LOPAS",
    "Password": "STI_LOPAS",
    "Photo": "../images/male.png"
  },
  {
    "voters_id": "2000416847",
    "Firstname": "GWEN FE",
    "Lastname": "LOPEZ",
    "Password": "STI_LOPEZ",
    "Photo": "../images/male.png"
  },
  {
    "voters_id": "2000464461",
    "Firstname": "ANGEL",
    "Lastname": "LUATON",
    "Password": "STI_LUATON",
    "Photo": "../images/male.png"
  },
  {
    "voters_id": "2000375335",
    "Firstname": "JOHN ANDREW",
    "Lastname": "LUMAWAG",
    "Password": "STI_LUMAWAG",
    "Photo": "../images/male.png"
  },
  {
    "voters_id": "2000425469",
    "Firstname": "JOHN PAULO",
    "Lastname": "LUZONG",
    "Password": "STI_LUZONG",
    "Photo": "../images/male.png"
  },
  {
    "voters_id": "2000366504",
    "Firstname": "NESTHY SHERANE",
    "Lastname": "MABINI",
    "Password": "STI_MABINI",
    "Photo": "../images/male.png"
  },
  {
    "voters_id": "2000474299",
    "Firstname": "GARY",
    "Lastname": "MACHATE",
    "Password": "STI_MACHATE",
    "Photo": "../images/male.png"
  },
  {
    "voters_id": "2000476334",
    "Firstname": "HARVEY IAN",
    "Lastname": "MAGALLON",
    "Password": "STI_MAGALLON",
    "Photo": "../images/male.png"
  },
  {
    "voters_id": "2000424330",
    "Firstname": "RECHAN",
    "Lastname": "MAGAN",
    "Password": "STI_MAGAN",
    "Photo": "../images/male.png"
  },
  {
    "voters_id": "2000421496",
    "Firstname": "JEWELDYN",
    "Lastname": "MAGAN",
    "Password": "STI_MAGAN",
    "Photo": "../images/male.png"
  },
  {
    "voters_id": "2000427434",
    "Firstname": "MARCIA JANE",
    "Lastname": "MAGGAY",
    "Password": "STI_MAGGAY",
    "Photo": "../images/male.png"
  },
  {
    "voters_id": "2000472932",
    "Firstname": "JOHAIBER",
    "Lastname": "MANANAGO",
    "Password": "STI_MANANAGO",
    "Photo": "../images/male.png"
  },
  {
    "voters_id": "2000470209",
    "Firstname": "NIEL CHRISTIAN",
    "Lastname": "MANAOG",
    "Password": "STI_MANAOG",
    "Photo": "../images/male.png"
  },
  {
    "voters_id": "2000474634",
    "Firstname": "RHAMYNAH ROSE",
    "Lastname": "MANONGSONG",
    "Password": "STI_MANONGSONG",
    "Photo": "../images/male.png"
  },
  {
    "voters_id": "2000470365",
    "Firstname": "JANNA- MAE",
    "Lastname": "MARQUEZ",
    "Password": "STI_MARQUEZ",
    "Photo": "../images/male.png"
  },
  {
    "voters_id": "2000473006",
    "Firstname": "ARIEL",
    "Lastname": "MARZO",
    "Password": "STI_MARZO",
    "Photo": "../images/male.png"
  },
  {
    "voters_id": "2000474529",
    "Firstname": "JOSHUA",
    "Lastname": "MASDO",
    "Password": "STI_MASDO",
    "Photo": "../images/male.png"
  },
  {
    "voters_id": "2000405156",
    "Firstname": "FAITH",
    "Lastname": "MASLAY",
    "Password": "STI_MASLAY",
    "Photo": "../images/male.png"
  },
  {
    "voters_id": "2000435510",
    "Firstname": "MERLITA",
    "Lastname": "MA\u00d1OZA",
    "Password": "STI_MA\u00d1OZA",
    "Photo": "../images/male.png"
  },
  {
    "voters_id": "2000431134",
    "Firstname": "MARIANITO JR.",
    "Lastname": "MEKITPEKIT",
    "Password": "STI_MEKITPEKIT",
    "Photo": "../images/male.png"
  },
  {
    "voters_id": "2000463618",
    "Firstname": "MELODY",
    "Lastname": "MELENDRES",
    "Password": "STI_MELENDRES",
    "Photo": "../images/male.png"
  },
  {
    "voters_id": "2000467804",
    "Firstname": "JAN MARTIN",
    "Lastname": "MENDOZA",
    "Password": "STI_MENDOZA",
    "Photo": "../images/male.png"
  },
  {
    "voters_id": "2000473536",
    "Firstname": "ARCEL JUDE",
    "Lastname": "MENDOZA",
    "Password": "STI_MENDOZA",
    "Photo": "../images/male.png"
  },
  {
    "voters_id": "2000469858",
    "Firstname": "JUSTIN LOUIZ",
    "Lastname": "MERCADER",
    "Password": "STI_MERCADER",
    "Photo": "../images/male.png"
  },
  {
    "voters_id": "2000373312",
    "Firstname": "MARY JHO",
    "Lastname": "MERCURIO",
    "Password": "STI_MERCURIO",
    "Photo": "../images/male.png"
  },
  {
    "voters_id": "2000467630",
    "Firstname": "LEWREEN VINCENT",
    "Lastname": "MEREGILDO",
    "Password": "STI_MEREGILDO",
    "Photo": "../images/male.png"
  },
  {
    "voters_id": "2000389428",
    "Firstname": "LUWIN",
    "Lastname": "MIANO",
    "Password": "STI_MIANO",
    "Photo": "../images/male.png"
  },
  {
    "voters_id": "2000475126",
    "Firstname": "NAJER",
    "Lastname": "MINANDANG",
    "Password": "STI_MINANDANG",
    "Photo": "../images/male.png"
  },
  {
    "voters_id": "2000455231",
    "Firstname": "DESIREE",
    "Lastname": "MONARES",
    "Password": "STI_MONARES",
    "Photo": "../images/male.png"
  },
  {
    "voters_id": "2000433656",
    "Firstname": "BIANCA",
    "Lastname": "MONTA\u00d1EZ",
    "Password": "STI_MONTA\u00d1EZ",
    "Photo": "../images/male.png"
  },
  {
    "voters_id": "2000473518",
    "Firstname": "DANIELLA MYCA",
    "Lastname": "MONTA\u00d1O",
    "Password": "STI_MONTA\u00d1O",
    "Photo": "../images/male.png"
  },
  {
    "voters_id": "2000464967",
    "Firstname": "JAMMER",
    "Lastname": "NACIONALES",
    "Password": "STI_NACIONALES",
    "Photo": "../images/male.png"
  },
  {
    "voters_id": "2000472641",
    "Firstname": "NICOLE",
    "Lastname": "NOYNAY",
    "Password": "STI_NOYNAY",
    "Photo": "../images/male.png"
  },
  {
    "voters_id": "2000468977",
    "Firstname": "ERLINDANIEL",
    "Lastname": "NUEVO",
    "Password": "STI_NUEVO",
    "Photo": "../images/male.png"
  },
  {
    "voters_id": "2000472601",
    "Firstname": "JONIL",
    "Lastname": "OBIADO",
    "Password": "STI_OBIADO",
    "Photo": "../images/male.png"
  },
  {
    "voters_id": "2000409738",
    "Firstname": "GIAN LEXTER",
    "Lastname": "OBRERO",
    "Password": "STI_OBRERO",
    "Photo": "../images/male.png"
  },
  {
    "voters_id": "2000473161",
    "Firstname": "MARK ADRIAN",
    "Lastname": "ONG",
    "Password": "STI_ONG",
    "Photo": "../images/male.png"
  },
  {
    "voters_id": "2000427766",
    "Firstname": "VENICE",
    "Lastname": "ONGCAL",
    "Password": "STI_ONGCAL",
    "Photo": "../images/male.png"
  },
  {
    "voters_id": "2000458108",
    "Firstname": "CHARMIN",
    "Lastname": "ONGCAL",
    "Password": "STI_ONGCAL",
    "Photo": "../images/male.png"
  },
  {
    "voters_id": "2000473725",
    "Firstname": "RYAN",
    "Lastname": "ORQUIN",
    "Password": "STI_ORQUIN",
    "Photo": "../images/male.png"
  },
  {
    "voters_id": "2000472103",
    "Firstname": "AIRRA",
    "Lastname": "ORTEGA",
    "Password": "STI_ORTEGA",
    "Photo": "../images/male.png"
  },
  {
    "voters_id": "2000474070",
    "Firstname": "ANDREI",
    "Lastname": "ORTILANO",
    "Password": "STI_ORTILANO",
    "Photo": "../images/male.png"
  },
  {
    "voters_id": "2000474101",
    "Firstname": "JEANNE LOUISE",
    "Lastname": "ORTIZ",
    "Password": "STI_ORTIZ",
    "Photo": "../images/male.png"
  },
  {
    "voters_id": "2000466450",
    "Firstname": "JUNBELL",
    "Lastname": "OSABEL",
    "Password": "STI_OSABEL",
    "Photo": "../images/male.png"
  },
  {
    "voters_id": "2000476153",
    "Firstname": "VER",
    "Lastname": "PAGHUBASAN",
    "Password": "STI_PAGHUBASAN",
    "Photo": "../images/male.png"
  },
  {
    "voters_id": "2000474324",
    "Firstname": "JOSE JR.",
    "Lastname": "PAGHUNASAN",
    "Password": "STI_PAGHUNASAN",
    "Photo": "../images/male.png"
  },
  {
    "voters_id": "2000424219",
    "Firstname": "NICOLE",
    "Lastname": "PAJARITO",
    "Password": "STI_PAJARITO",
    "Photo": "../images/male.png"
  },
  {
    "voters_id": "2000475431",
    "Firstname": "JONNEL",
    "Lastname": "PALLONES",
    "Password": "STI_PALLONES",
    "Photo": "../images/male.png"
  },
  {
    "voters_id": "2000476201",
    "Firstname": "JOSSYLLE",
    "Lastname": "PALLONES",
    "Password": "STI_PALLONES",
    "Photo": "../images/male.png"
  },
  {
    "voters_id": "2000476154",
    "Firstname": "JORICA",
    "Lastname": "PALOMERAS",
    "Password": "STI_PALOMERAS",
    "Photo": "../images/male.png"
  },
  {
    "voters_id": "2000472070",
    "Firstname": "JELLIANE ANNE",
    "Lastname": "PALOMERAS",
    "Password": "STI_PALOMERAS",
    "Photo": "../images/male.png"
  },
  {
    "voters_id": "2000467475",
    "Firstname": "FATIMA",
    "Lastname": "PANIMDIM",
    "Password": "STI_PANIMDIM",
    "Photo": "../images/male.png"
  },
  {
    "voters_id": "2000471318",
    "Firstname": "ARA MONIQUE",
    "Lastname": "PEDIMONTE",
    "Password": "STI_PEDIMONTE",
    "Photo": "../images/male.png"
  },
  {
    "voters_id": "2000395840",
    "Firstname": "MICHAEL",
    "Lastname": "PEDRADOJA",
    "Password": "STI_PEDRADOJA",
    "Photo": "../images/male.png"
  },
  {
    "voters_id": "2000459950",
    "Firstname": "JANELLA",
    "Lastname": "PEDRADOJA",
    "Password": "STI_PEDRADOJA",
    "Photo": "../images/male.png"
  },
  {
    "voters_id": "2000372710",
    "Firstname": "DONALIZA",
    "Lastname": "PENOTE",
    "Password": "STI_PENOTE",
    "Photo": "../images/male.png"
  },
  {
    "voters_id": "2000472707",
    "Firstname": "LARRY JAMES",
    "Lastname": "PERU",
    "Password": "STI_PERU",
    "Photo": "../images/male.png"
  },
  {
    "voters_id": "2000406281",
    "Firstname": "MAC ZANDREW",
    "Lastname": "PE\u00d1AOJAS",
    "Password": "STI_PE\u00d1AOJAS",
    "Photo": "../images/male.png"
  },
  {
    "voters_id": "2000416959",
    "Firstname": "JENIEVA",
    "Lastname": "PICORRO",
    "Password": "STI_PICORRO",
    "Photo": "../images/male.png"
  },
  {
    "voters_id": "2000474405",
    "Firstname": "RONELYN",
    "Lastname": "PILOTOS",
    "Password": "STI_PILOTOS",
    "Photo": "../images/male.png"
  },
  {
    "voters_id": "2000402160",
    "Firstname": "ANGELIE MEA",
    "Lastname": "PLANDEZ",
    "Password": "STI_PLANDEZ",
    "Photo": "../images/male.png"
  },
  {
    "voters_id": "2000470608",
    "Firstname": "ANGELICA",
    "Lastname": "PONSICA",
    "Password": "STI_PONSICA",
    "Photo": "../images/male.png"
  },
  {
    "voters_id": "2000389186",
    "Firstname": "JEZELL",
    "Lastname": "PORSUELO",
    "Password": "STI_PORSUELO",
    "Photo": "../images/male.png"
  },
  {
    "voters_id": "2000458278",
    "Firstname": "JADE",
    "Lastname": "PORSUELO",
    "Password": "STI_PORSUELO",
    "Photo": "../images/male.png"
  },
  {
    "voters_id": "2000425208",
    "Firstname": "IVAN",
    "Lastname": "PORTUGALIZA",
    "Password": "STI_PORTUGALIZA",
    "Photo": "../images/male.png"
  },
  {
    "voters_id": "2000435919",
    "Firstname": "JAY NICO",
    "Lastname": "POSTRADO",
    "Password": "STI_POSTRADO",
    "Photo": "../images/male.png"
  },
  {
    "voters_id": "2000416858",
    "Firstname": "MARIA ISABEL",
    "Lastname": "PRANDAS",
    "Password": "STI_PRANDAS",
    "Photo": "../images/male.png"
  },
  {
    "voters_id": "2000476262",
    "Firstname": "CAMILLE",
    "Lastname": "PUEBLOS",
    "Password": "STI_PUEBLOS",
    "Photo": "../images/male.png"
  },
  {
    "voters_id": "2000474357",
    "Firstname": "ALFREDO  JR.",
    "Lastname": "RAMA",
    "Password": "STI_RAMA",
    "Photo": "../images/male.png"
  },
  {
    "voters_id": "2000461243",
    "Firstname": "JEFFERSON",
    "Lastname": "RAMIREZ",
    "Password": "STI_RAMIREZ",
    "Photo": "../images/male.png"
  },
  {
    "voters_id": "2000434541",
    "Firstname": "JULIA MARIE",
    "Lastname": "REGINO",
    "Password": "STI_REGINO",
    "Photo": "../images/male.png"
  },
  {
    "voters_id": "2000435159",
    "Firstname": "JOHN LOUISE",
    "Lastname": "REPIQUE",
    "Password": "STI_REPIQUE",
    "Photo": "../images/male.png"
  },
  {
    "voters_id": "2000416248",
    "Firstname": "PRINCESS CECELIA",
    "Lastname": "RICALDE",
    "Password": "STI_RICALDE",
    "Photo": "../images/male.png"
  },
  {
    "voters_id": "2000437813",
    "Firstname": "MICHAELLA",
    "Lastname": "ROJAS",
    "Password": "STI_ROJAS",
    "Photo": "../images/male.png"
  },
  {
    "voters_id": "2000468391",
    "Firstname": "LEAJANE",
    "Lastname": "ROMANO",
    "Password": "STI_ROMANO",
    "Photo": "../images/male.png"
  },
  {
    "voters_id": "2000463185",
    "Firstname": "KENETH",
    "Lastname": "RONDEJA",
    "Password": "STI_RONDEJA",
    "Photo": "../images/male.png"
  },
  {
    "voters_id": "2000429554",
    "Firstname": "ADRIANA",
    "Lastname": "RUBANTE",
    "Password": "STI_RUBANTE",
    "Photo": "../images/male.png"
  },
  {
    "voters_id": "2000472875",
    "Firstname": "JAMILLE",
    "Lastname": "SABERON",
    "Password": "STI_SABERON",
    "Photo": "../images/male.png"
  },
  {
    "voters_id": "2000472646",
    "Firstname": "ROGIE MEL",
    "Lastname": "SAGORIO",
    "Password": "STI_SAGORIO",
    "Photo": "../images/male.png"
  },
  {
    "voters_id": "2000473593",
    "Firstname": "SEBASTIAN",
    "Lastname": "SALEM",
    "Password": "STI_SALEM",
    "Photo": "../images/male.png"
  },
  {
    "voters_id": "2000424191",
    "Firstname": "ALLAN JAMES",
    "Lastname": "SALES",
    "Password": "STI_SALES",
    "Photo": "../images/male.png"
  },
  {
    "voters_id": "2000475065",
    "Firstname": "LEE ANDRO",
    "Lastname": "SALUDARIO",
    "Password": "STI_SALUDARIO",
    "Photo": "../images/male.png"
  },
  {
    "voters_id": "2000425667",
    "Firstname": "AIRA",
    "Lastname": "SAMANTE",
    "Password": "STI_SAMANTE",
    "Photo": "../images/male.png"
  },
  {
    "voters_id": "2000415376",
    "Firstname": "KURT RUSSEL",
    "Lastname": "SANCHEZ",
    "Password": "STI_SANCHEZ",
    "Photo": "../images/male.png"
  },
  {
    "voters_id": "2000434792",
    "Firstname": "CANDY ASSESANDRA",
    "Lastname": "SANCHEZ",
    "Password": "STI_SANCHEZ",
    "Photo": "../images/male.png"
  },
  {
    "voters_id": "2000464679",
    "Firstname": "BOBBY",
    "Lastname": "SANDOVAL",
    "Password": "STI_SANDOVAL",
    "Photo": "../images/male.png"
  },
  {
    "voters_id": "2000399806",
    "Firstname": "JENILA MAE",
    "Lastname": "SANTIAGO",
    "Password": "STI_SANTIAGO",
    "Photo": "../images/male.png"
  },
  {
    "voters_id": "2000402632",
    "Firstname": "FREDIERIC JAMES",
    "Lastname": "SANTIAGO",
    "Password": "STI_SANTIAGO",
    "Photo": "../images/male.png"
  },
  {
    "voters_id": "2000412858",
    "Firstname": "MARIA ANGELA",
    "Lastname": "SARONG",
    "Password": "STI_SARONG",
    "Photo": "../images/male.png"
  },
  {
    "voters_id": "2000472596",
    "Firstname": "SHAIRA MAE",
    "Lastname": "SEBILLANO",
    "Password": "STI_SEBILLANO",
    "Photo": "../images/male.png"
  },
  {
    "voters_id": "2000470398",
    "Firstname": "FIONA",
    "Lastname": "SEBUSA",
    "Password": "STI_SEBUSA",
    "Photo": "../images/male.png"
  },
  {
    "voters_id": "2000473257",
    "Firstname": "RODEL",
    "Lastname": "SENANGOTE",
    "Password": "STI_SENANGOTE",
    "Photo": "../images/male.png"
  },
  {
    "voters_id": "2000423191",
    "Firstname": "ARNELYN",
    "Lastname": "SINTOS",
    "Password": "STI_SINTOS",
    "Photo": "../images/male.png"
  },
  {
    "voters_id": "2000426417",
    "Firstname": "RHEALENE",
    "Lastname": "SISIBAN",
    "Password": "STI_SISIBAN",
    "Photo": "../images/male.png"
  },
  {
    "voters_id": "2000417192",
    "Firstname": "MARIA THERESA",
    "Lastname": "SUAREZ",
    "Password": "STI_SUAREZ",
    "Photo": "../images/male.png"
  },
  {
    "voters_id": "2000466166",
    "Firstname": "KEITH",
    "Lastname": "SUMBISE",
    "Password": "STI_SUMBISE",
    "Photo": "../images/male.png"
  },
  {
    "voters_id": "2000473446",
    "Firstname": "BLANCE ASHLEY",
    "Lastname": "TALABOC",
    "Password": "STI_TALABOC",
    "Photo": "../images/male.png"
  },
  {
    "voters_id": "2000473354",
    "Firstname": "JAMAICA",
    "Lastname": "TANEO",
    "Password": "STI_TANEO",
    "Photo": "../images/male.png"
  },
  {
    "voters_id": "2000464689",
    "Firstname": "JOHN PAUL",
    "Lastname": "TARRAYO",
    "Password": "STI_TARRAYO",
    "Photo": "../images/male.png"
  },
  {
    "voters_id": "2000416211",
    "Firstname": "BABYLYN",
    "Lastname": "TARRAYO",
    "Password": "STI_TARRAYO",
    "Photo": "../images/male.png"
  },
  {
    "voters_id": "2000380411",
    "Firstname": "JOVIC MATTHIU",
    "Lastname": "TARRAYO",
    "Password": "STI_TARRAYO",
    "Photo": "../images/male.png"
  },
  {
    "voters_id": "2000468536",
    "Firstname": "MENNARD",
    "Lastname": "TAYACTAC",
    "Password": "STI_TAYACTAC",
    "Photo": "../images/male.png"
  },
  {
    "voters_id": "2000431541",
    "Firstname": "KRISTINE",
    "Lastname": "TENEDERO",
    "Password": "STI_TENEDERO",
    "Photo": "../images/male.png"
  },
  {
    "voters_id": "2000460149",
    "Firstname": "RAIN VALEN",
    "Lastname": "TINGZON",
    "Password": "STI_TINGZON",
    "Photo": "../images/male.png"
  },
  {
    "voters_id": "2000475688",
    "Firstname": "RONA",
    "Lastname": "TOBINO",
    "Password": "STI_TOBINO",
    "Photo": "../images/male.png"
  },
  {
    "voters_id": "2000416988",
    "Firstname": "THYLER QUIM",
    "Lastname": "TORCULAS",
    "Password": "STI_TORCULAS",
    "Photo": "../images/male.png"
  },
  {
    "voters_id": "2000459875",
    "Firstname": "JENRIC JOHN",
    "Lastname": "TRIGO",
    "Password": "STI_TRIGO",
    "Photo": "../images/male.png"
  },
  {
    "voters_id": "2000459886",
    "Firstname": "JADE MC NEAL",
    "Lastname": "TRIGO",
    "Password": "STI_TRIGO",
    "Photo": "../images/male.png"
  },
  {
    "voters_id": "2000472725",
    "Firstname": "AISEL LUJIELLE",
    "Lastname": "TUPA",
    "Password": "STI_TUPA",
    "Photo": "../images/male.png"
  },
  {
    "voters_id": "2000431609",
    "Firstname": "WENDELL JOHN",
    "Lastname": "TURLA",
    "Password": "STI_TURLA",
    "Photo": "../images/male.png"
  },
  {
    "voters_id": "2000462633",
    "Firstname": "MARC  ANDRE",
    "Lastname": "UY",
    "Password": "STI_UY",
    "Photo": "../images/male.png"
  },
  {
    "voters_id": "2000425344",
    "Firstname": "MC GRADY",
    "Lastname": "VILLA",
    "Password": "STI_VILLA",
    "Photo": "../images/male.png"
  },
  {
    "voters_id": "2000470347",
    "Firstname": "EUGEL  ANTHONY",
    "Lastname": "VILLANUEVA",
    "Password": "STI_VILLANUEVA",
    "Photo": "../images/male.png"
  },
  {
    "voters_id": "2000424707",
    "Firstname": "RAVEN",
    "Lastname": "VILLEGAS",
    "Password": "STI_VILLEGAS",
    "Photo": "../images/male.png"
  },
  {
    "voters_id": "2000417529",
    "Firstname": "JERALD",
    "Lastname": "VILLENAS",
    "Password": "STI_VILLENAS",
    "Photo": "../images/male.png"
  },
  {
    "voters_id": "2000416969",
    "Firstname": "ERVINE",
    "Lastname": "YABAO",
    "Password": "STI_YABAO",
    "Photo": "../images/male.png"
  },
  {
    "voters_id": "2000472312",
    "Firstname": "AIESHA PHYLISS",
    "Lastname": "YANUARIO",
    "Password": "STI_YANUARIO",
    "Photo": "../images/male.png"
  },
  {
    "voters_id": "2000472751",
    "Firstname": "FARES",
    "Lastname": "YAUDER",
    "Password": "STI_YAUDER",
    "Photo": "../images/male.png"
  },
  {
    "voters_id": "2000473985",
    "Firstname": "MICHAEL",
    "Lastname": "YBALAN",
    "Password": "STI_YBALAN",
    "Photo": "../images/male.png"
  },
  {
    "voters_id": "2000463577",
    "Firstname": "MAE",
    "Lastname": "YBA\u00d1EZ",
    "Password": "STI_YBA\u00d1EZ",
    "Photo": "../images/male.png"
  },
  {
    "voters_id": "2000470885",
    "Firstname": "MARY ANN",
    "Lastname": "YGBUHAY",
    "Password": "STI_YGBUHAY",
    "Photo": "../images/male.png"
  },
  {
    "voters_id": "2000427095",
    "Firstname": "AENELLE MARIE",
    "Lastname": "YU",
    "Password": "STI_YU",
    "Photo": "../images/male.png"
  },
  {
    "voters_id": "2000463923",
    "Firstname": "MARY JOY",
    "Lastname": "ZACATE",
    "Password": "STI_ZACATE",
    "Photo": "../images/male.png"
  },
  {
    "voters_id": "2000472906",
    "Firstname": "LALIEN",
    "Lastname": "ZAMORA",
    "Password": "STI_ZAMORA",
    "Photo": "../images/male.png"
  }
]